[
    {"id": 0,
    "name": "Bruce Park",
    "coordinate": []
    },
    {
        "id": 0,
        "name": "Bunn's Creek Centennial Park",
        "coordinate": []
    },
    {
        "id": 0,
        "name": "Crescent Drive Park",
        "coordinate": []
    },
    {
        "id": 0,
        "name": "Fraser's Grove Park",
        "coordinate": []
    },
    {
        "id": 0,
        "name": "Harbourview Park & Recreation Complex",
        "coordinate": []
    },
    {
        "id": 0,
        "name": "Kildonan Park",
        "coordinate": []
    },
    {
        "id": 0,
        "name": "Kings Park",
        "coordinate": []
    },
    {
        "id": 0,
        "name": "La Barrier Park",
        "coordinate": []
    },
    {
        "id": 0,
        "name": "Little Mountain Park",
        "coordinate": []
    },
    {
        "id": 0,
        "name": "Provencher Park",
        "coordinate": []
    },
    {
        "id": 0,
        "name": "St. John's Park",
        "coordinate": []
    },
    {
        "id": 0,
        "name": "St. Vital Park",
        "coordinate": []
    },
    {
        "id": 0,
        "name": "Vimy Ridge Memorial Park",
        "coordinate": []
    },
    {
        "id": 0,
        "name": "Whittier Park",
        "coordinate": []
    },
    {
        "id": 0,
        "name": "Assiniboine Park",
        "coordinate": []
    }
    
]